pytools_args/__init__.py
pytools_args/core.py
pytools_args-0.1.0.dist-info/DESCRIPTION.rst
pytools_args-0.1.0.dist-info/METADATA
pytools_args-0.1.0.dist-info/RECORD
pytools_args-0.1.0.dist-info/WHEEL
pytools_args-0.1.0.dist-info/metadata.json
pytools_args-0.1.0.dist-info/top_level.txt
