Metadata-Version: 2.0
Name: pytools-args
Version: 0.1.0
Summary: A small helper module for detecting, evaluating and processing arguments.
Home-page: https://github.com/pytools/pytools-args
Author: Richard King
Author-email: richrdkng@gmail.com
License: MIT
Keywords: arguments argument args pytools development
Platform: UNKNOWN
Classifier: Development Status :: 3 - Alpha
Classifier: Intended Audience :: Developers
Classifier: Topic :: Software Development
Classifier: License :: OSI Approved :: MIT License
Classifier: Programming Language :: Python :: 2
Classifier: Programming Language :: Python :: 2.7
Classifier: Programming Language :: Python :: 3
Classifier: Programming Language :: Python :: 3.3
Classifier: Programming Language :: Python :: 3.4
Classifier: Programming Language :: Python :: 3.5
